{"type":"FeatureCollection","features":[{"id":"339285309","type":"Feature","properties":{"height":6,"levels":2,"color":"#f2f5f7","roofShape":"flat","building":"r4807851"},"geometry":{"type":"Polygon","coordinates":[[[13.380916,52.389279],[13.380923,52.389334],[13.380973,52.389332],[13.380966,52.389277],[13.380916,52.389279]]]}},{"id":"339285319","type":"Feature","properties":{"height":6,"levels":2,"color":"#f2f5f7","roofShape":"flat","building":"r4807843"},"geometry":{"type":"Polygon","coordinates":[[[13.381058,52.390402],[13.381068,52.390456],[13.381118,52.390453],[13.381108,52.390398],[13.381058,52.390402]]]}},{"id":"339285314","type":"Feature","properties":{"height":6,"levels":2,"color":"#f2f5f7","roofShape":"flat","building":"r4807849"},"geometry":{"type":"Polygon","coordinates":[[[13.380903,52.389087],[13.380906,52.389142],[13.380956,52.389141],[13.380954,52.389086],[13.380903,52.389087]]]}},{"id":"339285323","type":"Feature","properties":{"height":6,"levels":2,"color":"#f2f5f7","roofShape":"flat","building":"r4807843"},"geometry":{"type":"Polygon","coordinates":[[[13.381048,52.39035],[13.381058,52.390402],[13.381108,52.390398],[13.381098,52.390346],[13.381048,52.39035]]]}},{"id":"339285302","type":"Feature","properties":{"height":6,"levels":2,"color":"#f2f5f7","roofShape":"flat","building":"r4807845"},"geometry":{"type":"Polygon","coordinates":[[[13.380975,52.389789],[13.380982,52.389841],[13.381032,52.389838],[13.381025,52.389786],[13.380975,52.389789]]]}},{"id":"339285311","type":"Feature","properties":{"height":6,"levels":2,"color":"#f2f5f7","roofShape":"flat","building":"r4807852"},"geometry":{"type":"Polygon","coordinates":[[[13.381023,52.390212],[13.38103,52.390267],[13.38108,52.390264],[13.381073,52.390209],[13.381023,52.390212]]]}},{"id":"339285332","type":"Feature","properties":{"height":11,"levels":2,"color":"#f2f5f7","roofMaterial":"roof_tiles","roofColor":"#acabaf","roofShape":"skillion","roofLevels":1,"roofDirection":91.60000000000002,"building":"r4807849"},"geometry":{"type":"Polygon","coordinates":[[[13.380951,52.389033],[13.380956,52.389141],[13.381062,52.389139],[13.381057,52.389032],[13.380951,52.389033]]]}},{"id":"339285325","type":"Feature","properties":{"height":6,"levels":2,"color":"#f2f5f7","roofShape":"flat","building":"r4807849"},"geometry":{"type":"Polygon","coordinates":[[[13.380901,52.389034],[13.380903,52.389087],[13.380954,52.389086],[13.380951,52.389033],[13.380901,52.389034]]]}},{"id":"339285303","type":"Feature","properties":{"height":6,"levels":2,"color":"#f2f5f7","roofShape":"flat","building":"r4807844"},"geometry":{"type":"Polygon","coordinates":[[[13.380958,52.389654],[13.380965,52.389709],[13.381015,52.389706],[13.381008,52.389652],[13.380958,52.389654]]]}},{"id":"339285307","type":"Feature","properties":{"height":6,"levels":2,"color":"#f2f5f7","roofShape":"flat","building":"r4807844"},"geometry":{"type":"Polygon","coordinates":[[[13.380951,52.389602],[13.380958,52.389654],[13.381008,52.389652],[13.381001,52.389599],[13.380951,52.389602]]]}},{"id":"339285316","type":"Feature","properties":{"height":6,"levels":2,"color":"#f2f5f7","roofShape":"flat","building":"r4807850"},"geometry":{"type":"Polygon","coordinates":[[[13.380992,52.390027],[13.380999,52.390082],[13.381049,52.390079],[13.381042,52.390025],[13.380992,52.390027]]]}},{"id":"339285329","type":"Feature","properties":{"height":11,"levels":2,"color":"#f2f5f7","roofMaterial":"roof_tiles","roofColor":"#acabaf","roofLevels":1,"building":"r4807843"},"geometry":{"type":"Polygon","coordinates":[[[13.381098,52.390346],[13.381118,52.390453],[13.381223,52.390445],[13.381203,52.390339],[13.381098,52.390346]]]}},{"id":"339285337","type":"Feature","properties":{"height":11,"levels":2,"color":"#f2f5f7","roofMaterial":"roof_tiles","roofColor":"#acabaf","roofLevels":1,"building":"r4807851"},"geometry":{"type":"Polygon","coordinates":[[[13.380959,52.389225],[13.380973,52.389332],[13.381078,52.389327],[13.381064,52.38922],[13.380959,52.389225]]]}},{"id":"339285326","type":"Feature","properties":{"height":6,"levels":2,"color":"#f2f5f7","roofShape":"flat","building":"r4807850"},"geometry":{"type":"Polygon","coordinates":[[[13.380985,52.389975],[13.380992,52.390027],[13.381042,52.390025],[13.381035,52.389973],[13.380985,52.389975]]]}},{"id":"339285333","type":"Feature","properties":{"height":11,"levels":2,"color":"#f2f5f7","roofMaterial":"roof_tiles","roofColor":"#acabaf","roofShape":"skillion","roofLevels":1,"roofDirection":94.60000000000002,"building":"r4807850"},"geometry":{"type":"Polygon","coordinates":[[[13.381035,52.389973],[13.381049,52.390079],[13.381154,52.390074],[13.38114,52.389968],[13.381035,52.389973]]]}},{"id":"339285336","type":"Feature","properties":{"height":11,"levels":2,"color":"#f2f5f7","roofMaterial":"roof_tiles","roofColor":"#acabaf","roofShape":"skillion","roofLevels":1,"roofDirection":94.60000000000002,"building":"r4807847"},"geometry":{"type":"Polygon","coordinates":[[[13.380982,52.389412],[13.380996,52.389519],[13.381101,52.389514],[13.381087,52.389407],[13.380982,52.389412]]]}},{"id":"339285304","type":"Feature","properties":{"height":6,"levels":2,"color":"#f2f5f7","roofShape":"flat","building":"r4807847"},"geometry":{"type":"Polygon","coordinates":[[[13.380939,52.389467],[13.380946,52.389522],[13.380996,52.389519],[13.380989,52.389465],[13.380939,52.389467]]]}},{"id":"229441702","type":"Feature","properties":{"levels":2,"type":"terrace"},"geometry":{"type":"Polygon","coordinates":[[[13.380657,52.3925],[13.380669,52.39255],[13.380805,52.392537],[13.380793,52.392488],[13.380657,52.3925]]]}},{"id":"229441684","type":"Feature","properties":{"levels":2,"type":"terrace"},"geometry":{"type":"Polygon","coordinates":[[[13.380771,52.392978],[13.380782,52.393024],[13.380918,52.393011],[13.380907,52.392966],[13.380771,52.392978]]]}},{"id":"229441629","type":"Feature","properties":{"levels":1,"type":"terrace"},"geometry":{"type":"Polygon","coordinates":[[[13.381346,52.392459],[13.381364,52.392536],[13.381439,52.392531],[13.381443,52.392557],[13.38154,52.392548],[13.381529,52.392498],[13.381512,52.392499],[13.381499,52.392443],[13.381346,52.392459]]]}},{"id":"229441612","type":"Feature","properties":{"levels":2,"type":"terrace"},"geometry":{"type":"Polygon","coordinates":[[[13.380868,52.393356],[13.38088,52.393403],[13.381014,52.39339],[13.381003,52.393344],[13.380868,52.393356]]]}},{"id":"229441613","type":"Feature","properties":{"levels":2,"type":"terrace"},"geometry":{"type":"Polygon","coordinates":[[[13.380962,52.393734],[13.380975,52.393785],[13.38111,52.393773],[13.381097,52.393721],[13.380962,52.393734]]]}},{"id":"229441685","type":"Feature","properties":{"levels":2,"type":"terrace"},"geometry":{"type":"Polygon","coordinates":[[[13.380419,52.391414],[13.380437,52.391484],[13.380572,52.391471],[13.380555,52.391401],[13.380419,52.391414]]]}},{"id":"229441680","type":"Feature","properties":{"levels":2,"type":"terrace"},"geometry":{"type":"Polygon","coordinates":[[[13.380432,52.391616],[13.380448,52.39168],[13.380588,52.391667],[13.380572,52.391603],[13.380432,52.391616]]]}},{"id":"229441664","type":"Feature","properties":{"levels":2,"type":"terrace"},"geometry":{"type":"Polygon","coordinates":[[[13.381078,52.390946],[13.381101,52.391043],[13.381106,52.391043],[13.381105,52.391037],[13.381138,52.391034],[13.38114,52.39104],[13.381183,52.391036],[13.38116,52.390938],[13.381078,52.390946]]]}},{"id":"229441639","type":"Feature","properties":{"levels":1},"geometry":{"type":"Polygon","coordinates":[[[13.381041,52.391231],[13.381049,52.391262],[13.381075,52.391259],[13.381082,52.391286],[13.381198,52.391274],[13.381175,52.391185],[13.381058,52.391196],[13.381067,52.391228],[13.381041,52.391231]]]}},{"id":"229441624","type":"Feature","properties":{"levels":2,"type":"terrace"},"geometry":{"type":"Polygon","coordinates":[[[13.380536,52.392013],[13.380551,52.392075],[13.380684,52.392063],[13.380669,52.392],[13.380536,52.392013]]]}},{"id":"229441605","type":"Feature","properties":{"levels":2,"type":"terrace"},"geometry":{"type":"Polygon","coordinates":[[[13.380482,52.391814],[13.380498,52.391877],[13.380634,52.391865],[13.380618,52.391802],[13.380482,52.391814]]]}},{"id":"229441600","type":"Feature","properties":{"levels":1},"geometry":{"type":"Polygon","coordinates":[[[13.381339,52.392166],[13.38135,52.392213],[13.381553,52.392195],[13.381541,52.392146],[13.381492,52.39215],[13.381473,52.392075],[13.38134,52.392087],[13.381359,52.392163],[13.381339,52.392166]]]}},{"id":"229441561","type":"Feature","properties":{"levels":1},"geometry":{"type":"Polygon","coordinates":[[[13.381273,52.391925],[13.381299,52.39203],[13.381409,52.39202],[13.381407,52.392012],[13.381436,52.392009],[13.381438,52.392017],[13.381552,52.392006],[13.381525,52.391901],[13.381411,52.391911],[13.381413,52.391919],[13.381383,52.391922],[13.381382,52.391915],[13.381273,52.391925]]]}},{"id":"229441562","type":"Feature","properties":{"levels":1},"geometry":{"type":"Polygon","coordinates":[[[13.381329,52.392307],[13.38135,52.392387],[13.381509,52.392372],[13.381489,52.392291],[13.381447,52.392295],[13.381442,52.392276],[13.38138,52.392281],[13.381385,52.392302],[13.381329,52.392307]]]}},{"id":"229441696","type":"Feature","properties":{"levels":2,"type":"detached"},"geometry":{"type":"Polygon","coordinates":[[[13.381234,52.39137],[13.381254,52.391463],[13.381421,52.39145],[13.381404,52.391376],[13.381344,52.39138],[13.381339,52.391361],[13.381234,52.39137]]]}},{"id":"339285324","type":"Feature","properties":{"height":6,"levels":2,"color":"#f2f5f7","roofShape":"flat","building":"r4807852"},"geometry":{"type":"Polygon","coordinates":[[[13.381016,52.39016],[13.381023,52.390212],[13.381073,52.390209],[13.381066,52.390157],[13.381016,52.39016]]]}},{"id":"339285327","type":"Feature","properties":{"height":6,"levels":2,"color":"#f2f5f7","roofShape":"flat","building":"r4807845"},"geometry":{"type":"Polygon","coordinates":[[[13.380982,52.389841],[13.380989,52.389896],[13.381039,52.389893],[13.381032,52.389838],[13.380982,52.389841]]]}},{"id":"229441573","type":"Feature","properties":{"levels":2,"type":"detached"},"geometry":{"type":"Polygon","coordinates":[[[13.381169,52.391552],[13.381196,52.391659],[13.381341,52.391646],[13.381315,52.391539],[13.381169,52.391552]]]}},{"id":"339285310","type":"Feature","properties":{"height":6,"levels":2,"color":"#f2f5f7","roofShape":"flat","building":"r4807847"},"geometry":{"type":"Polygon","coordinates":[[[13.380932,52.389415],[13.380939,52.389467],[13.380989,52.389465],[13.380982,52.389412],[13.380932,52.389415]]]}},{"id":"339285320","type":"Feature","properties":{"height":6,"levels":2,"color":"#f2f5f7","roofShape":"flat","building":"r4807851"},"geometry":{"type":"Polygon","coordinates":[[[13.380909,52.389227],[13.380916,52.389279],[13.380966,52.389277],[13.380959,52.389225],[13.380909,52.389227]]]}},{"id":"229441579","type":"Feature","properties":{"levels":2,"type":"detached"},"geometry":{"type":"Polygon","coordinates":[[[13.381214,52.39174],[13.381239,52.391842],[13.381352,52.391832],[13.381328,52.391731],[13.38131,52.391732],[13.381307,52.39172],[13.381267,52.391724],[13.38127,52.391735],[13.381214,52.39174]]]}},{"id":"320823084","type":"Feature","properties":{"levels":2,"type":"terrace"},"geometry":{"type":"Polygon","coordinates":[[[13.380418,52.391561],[13.380432,52.391616],[13.380572,52.391603],[13.380558,52.391548],[13.380418,52.391561]]]}},{"id":"320823081","type":"Feature","properties":{"levels":2,"type":"terrace"},"geometry":{"type":"Polygon","coordinates":[[[13.380935,52.393472],[13.380949,52.393527],[13.381081,52.393515],[13.381068,52.39346],[13.380935,52.393472]]]}},{"id":"320823041","type":"Feature","properties":{"levels":2,"type":"terrace"},"geometry":{"type":"Polygon","coordinates":[[[13.380521,52.391953],[13.380536,52.392013],[13.380669,52.392],[13.380654,52.391941],[13.380521,52.391953]]]}},{"id":"320823034","type":"Feature","properties":{"levels":2,"type":"terrace"},"geometry":{"type":"Polygon","coordinates":[[[13.380842,52.393094],[13.380856,52.393149],[13.380989,52.393137],[13.380975,52.393081],[13.380842,52.393094]]]}},{"id":"320823016","type":"Feature","properties":{"levels":2,"type":"terrace"},"geometry":{"type":"Polygon","coordinates":[[[13.380725,52.392619],[13.380738,52.392671],[13.380866,52.392659],[13.380853,52.392607],[13.380725,52.392619]]]}},{"id":"320822987","type":"Feature","properties":{"levels":2,"type":"terrace"},"geometry":{"type":"Polygon","coordinates":[[[13.380468,52.391755],[13.380482,52.391814],[13.380618,52.391802],[13.380604,52.391743],[13.380468,52.391755]]]}},{"id":"320822935","type":"Feature","properties":{"levels":1,"type":"garage"},"geometry":{"type":"Polygon","coordinates":[[[13.38118,52.391203],[13.381198,52.391274],[13.381181,52.391276],[13.381184,52.391287],[13.381265,52.391279],[13.381243,52.391197],[13.38118,52.391203]]]}},{"id":"320822934","type":"Feature","properties":{"levels":2,"type":"terrace"},"geometry":{"type":"Polygon","coordinates":[[[13.380605,52.392144],[13.380618,52.392193],[13.38075,52.392181],[13.380737,52.392131],[13.380605,52.392144]]]}},{"id":"320822911","type":"Feature","properties":{"levels":2,"type":"terrace"},"geometry":{"type":"Polygon","coordinates":[[[13.380856,52.393149],[13.380869,52.3932],[13.381001,52.393188],[13.380989,52.393137],[13.380856,52.393149]]]}},{"id":"320822897","type":"Feature","properties":{"levels":1,"type":"garage"},"geometry":{"type":"Polygon","coordinates":[[[13.381088,52.393775],[13.3811,52.393824],[13.381145,52.39382],[13.381136,52.393771],[13.381088,52.393775]]]}},{"id":"320822853","type":"Feature","properties":{"levels":2,"type":"terrace"},"geometry":{"type":"Polygon","coordinates":[[[13.380751,52.392721],[13.380763,52.392773],[13.380891,52.392761],[13.380878,52.392709],[13.380751,52.392721]]]}},{"id":"320822837","type":"Feature","properties":{"levels":2,"type":"terrace"},"geometry":{"type":"Polygon","coordinates":[[[13.38063,52.392244],[13.380643,52.392295],[13.380775,52.392283],[13.380762,52.392231],[13.38063,52.392244]]]}},{"id":"320822825","type":"Feature","properties":{"levels":2,"type":"terrace"},"geometry":{"type":"Polygon","coordinates":[[[13.380606,52.392299],[13.380619,52.39235],[13.380755,52.392338],[13.380742,52.392286],[13.380606,52.392299]]]}},{"id":"320822823","type":"Feature","properties":{"levels":2,"type":"terrace"},"geometry":{"type":"Polygon","coordinates":[[[13.380406,52.391362],[13.380419,52.391414],[13.380555,52.391401],[13.380542,52.391349],[13.380406,52.391362]]]}},{"id":"320822779","type":"Feature","properties":{"levels":2,"type":"terrace"},"geometry":{"type":"Polygon","coordinates":[[[13.38072,52.392777],[13.380733,52.392828],[13.380869,52.392816],[13.380856,52.392764],[13.38072,52.392777]]]}},{"id":"320822775","type":"Feature","properties":{"levels":1,"type":"garage"},"geometry":{"type":"Polygon","coordinates":[[[13.380965,52.393786],[13.380977,52.393835],[13.381018,52.393832],[13.381006,52.393783],[13.380965,52.393786]]]}},{"id":"320822767","type":"Feature","properties":{"levels":2,"type":"terrace"},"geometry":{"type":"Polygon","coordinates":[[[13.380831,52.393204],[13.380844,52.393256],[13.380978,52.393243],[13.380965,52.393192],[13.380831,52.393204]]]}},{"id":"320822754","type":"Feature","properties":{"levels":2,"type":"terrace"},"geometry":{"type":"Polygon","coordinates":[[[13.380949,52.393527],[13.380961,52.393578],[13.381094,52.393566],[13.381081,52.393515],[13.380949,52.393527]]]}},{"id":"320822727","type":"Feature","properties":{"levels":2,"type":"terrace"},"geometry":{"type":"Polygon","coordinates":[[[13.380924,52.393582],[13.380937,52.393634],[13.381072,52.393621],[13.381059,52.39357],[13.380924,52.393582]]]}},{"id":"320822709","type":"Feature","properties":{"levels":1,"type":"garage"},"geometry":{"type":"Polygon","coordinates":[[[13.380616,52.392115],[13.380622,52.392142],[13.380693,52.392135],[13.380687,52.392109],[13.380616,52.392115]]]}},{"id":"320822707","type":"Feature","properties":{"levels":1,"type":"garage"},"geometry":{"type":"Polygon","coordinates":[[[13.381044,52.393952],[13.381056,52.394001],[13.381096,52.393998],[13.381085,52.393949],[13.381044,52.393952]]]}},{"id":"320822685","type":"Feature","properties":{"levels":1,"type":"garage"},"geometry":{"type":"Polygon","coordinates":[[[13.381006,52.393783],[13.381018,52.393832],[13.381059,52.393828],[13.381047,52.393779],[13.381006,52.393783]]]}},{"id":"320822673","type":"Feature","properties":{"levels":1,"type":"garage"},"geometry":{"type":"Polygon","coordinates":[[[13.381003,52.393956],[13.381015,52.394005],[13.381056,52.394001],[13.381044,52.393952],[13.381003,52.393956]]]}},{"id":"320822664","type":"Feature","properties":{"levels":1,"type":"garage"},"geometry":{"type":"Polygon","coordinates":[[[13.380734,52.392593],[13.38074,52.392618],[13.380812,52.392611],[13.380806,52.392585],[13.380734,52.392593]]]}},{"id":"320822654","type":"Feature","properties":{"levels":1,"type":"garage"},"geometry":{"type":"Polygon","coordinates":[[[13.380459,52.391482],[13.380463,52.391498],[13.380533,52.391492],[13.380529,52.391475],[13.380459,52.391482]]]}},{"id":"320822651","type":"Feature","properties":{"levels":1,"type":"garage"},"geometry":{"type":"Polygon","coordinates":[[[13.381074,52.3939],[13.381085,52.393949],[13.381126,52.393945],[13.381115,52.393896],[13.381074,52.3939]]]}},{"id":"320822642","type":"Feature","properties":{"levels":1,"type":"garage"},"geometry":{"type":"Polygon","coordinates":[[[13.38084,52.393019],[13.380847,52.39305],[13.380918,52.393043],[13.38091,52.393012],[13.38084,52.393019]]]}},{"id":"320822625","type":"Feature","properties":{"levels":1,"type":"garage"},"geometry":{"type":"Polygon","coordinates":[[[13.380568,52.391921],[13.380574,52.391948],[13.380643,52.391941],[13.380637,52.391915],[13.380568,52.391921]]]}},{"id":"320822607","type":"Feature","properties":{"levels":2,"type":"terrace"},"geometry":{"type":"Polygon","coordinates":[[[13.380758,52.392928],[13.380771,52.392978],[13.380907,52.392966],[13.380894,52.392916],[13.380758,52.392928]]]}},{"id":"320822594","type":"Feature","properties":{"levels":2,"type":"terrace"},"geometry":{"type":"Polygon","coordinates":[[[13.380949,52.393684],[13.380962,52.393734],[13.381097,52.393721],[13.381084,52.393671],[13.380949,52.393684]]]}},{"id":"320822542","type":"Feature","properties":{"levels":2,"type":"terrace"},"geometry":{"type":"Polygon","coordinates":[[[13.380644,52.39245],[13.380657,52.3925],[13.380793,52.392488],[13.38078,52.392438],[13.380644,52.39245]]]}},{"id":"320822529","type":"Feature","properties":{"levels":1,"type":"garage"},"geometry":{"type":"Polygon","coordinates":[[[13.381033,52.393903],[13.381044,52.393952],[13.381085,52.393949],[13.381074,52.3939],[13.381033,52.393903]]]}},{"id":"320822498","type":"Feature","properties":{"levels":1,"type":"garage"},"geometry":{"type":"Polygon","coordinates":[[[13.38091,52.393914],[13.380921,52.393963],[13.380962,52.39396],[13.380951,52.39391],[13.38091,52.393914]]]}},{"id":"320822490","type":"Feature","properties":{"levels":2,"type":"terrace"},"geometry":{"type":"Polygon","coordinates":[[[13.380844,52.393256],[13.380856,52.393306],[13.38099,52.393294],[13.380978,52.393243],[13.380844,52.393256]]]}},{"id":"320822483","type":"Feature","properties":{"levels":1,"type":"garage"},"geometry":{"type":"Polygon","coordinates":[[[13.380883,52.393794],[13.380895,52.393843],[13.380936,52.393839],[13.380924,52.39379],[13.380883,52.393794]]]}},{"id":"320822480","type":"Feature","properties":{"levels":2,"type":"terrace"},"geometry":{"type":"Polygon","coordinates":[[[13.380746,52.392878],[13.380758,52.392928],[13.380894,52.392916],[13.380882,52.392866],[13.380746,52.392878]]]}},{"id":"320822454","type":"Feature","properties":{"levels":1,"type":"garage"},"geometry":{"type":"Polygon","coordinates":[[[13.380921,52.393963],[13.380933,52.394012],[13.380974,52.394008],[13.380962,52.39396],[13.380921,52.393963]]]}},{"id":"320822445","type":"Feature","properties":{"levels":1,"type":"garage"},"geometry":{"type":"Polygon","coordinates":[[[13.380723,52.392545],[13.380729,52.392572],[13.380803,52.392565],[13.380797,52.392538],[13.380723,52.392545]]]}},{"id":"320822442","type":"Feature","properties":{"levels":1,"type":"garage"},"geometry":{"type":"Polygon","coordinates":[[[13.380469,52.391523],[13.380477,52.391555],[13.380547,52.391549],[13.380539,52.391517],[13.380469,52.391523]]]}},{"id":"320822436","type":"Feature","properties":{"levels":2,"type":"terrace"},"geometry":{"type":"Polygon","coordinates":[[[13.380856,52.393306],[13.380868,52.393356],[13.381003,52.393344],[13.38099,52.393294],[13.380856,52.393306]]]}},{"id":"320822433","type":"Feature","properties":{"levels":2,"type":"terrace"},"geometry":{"type":"Polygon","coordinates":[[[13.380738,52.392671],[13.380751,52.392721],[13.380878,52.392709],[13.380866,52.392659],[13.380738,52.392671]]]}},{"id":"320822431","type":"Feature","properties":{"levels":1,"type":"garage"},"geometry":{"type":"Polygon","coordinates":[[[13.380924,52.39379],[13.380936,52.393839],[13.380977,52.393835],[13.380965,52.393786],[13.380924,52.39379]]]}},{"id":"320822412","type":"Feature","properties":{"levels":1,"type":"garage"},"geometry":{"type":"Polygon","coordinates":[[[13.380934,52.393398],[13.380941,52.393428],[13.381013,52.393421],[13.381005,52.393391],[13.380934,52.393398]]]}},{"id":"320822319","type":"Feature","properties":{"levels":1,"type":"garage"},"geometry":{"type":"Polygon","coordinates":[[[13.380507,52.391675],[13.380512,52.391697],[13.38058,52.391691],[13.380575,52.391668],[13.380507,52.391675]]]}},{"id":"320822396","type":"Feature","properties":{"levels":1,"type":"garage"},"geometry":{"type":"Polygon","coordinates":[[[13.381011,52.391108],[13.381017,52.391133],[13.381101,52.391125],[13.381095,52.3911],[13.381011,52.391108]]]}},{"id":"320822390","type":"Feature","properties":{"levels":1,"type":"garage"},"geometry":{"type":"Polygon","coordinates":[[[13.380946,52.393449],[13.380952,52.393471],[13.381023,52.393464],[13.381018,52.393442],[13.380946,52.393449]]]}},{"id":"320822384","type":"Feature","properties":{"levels":1,"type":"garage"},"geometry":{"type":"Polygon","coordinates":[[[13.380463,52.391498],[13.380469,52.391523],[13.380539,52.391517],[13.380533,52.391492],[13.380463,52.391498]]]}},{"id":"320822370","type":"Feature","properties":{"levels":1,"type":"garage"},"geometry":{"type":"Polygon","coordinates":[[[13.380853,52.393071],[13.380858,52.393092],[13.380928,52.393085],[13.380923,52.393064],[13.380853,52.393071]]]}},{"id":"320822365","type":"Feature","properties":{"levels":2,"type":"terrace"},"geometry":{"type":"Polygon","coordinates":[[[13.380618,52.392193],[13.38063,52.392244],[13.380762,52.392231],[13.38075,52.392181],[13.380618,52.392193]]]}},{"id":"320822296","type":"Feature","properties":{"levels":1,"type":"garage"},"geometry":{"type":"Polygon","coordinates":[[[13.380512,52.391697],[13.380518,52.391722],[13.380587,52.391716],[13.38058,52.391691],[13.380512,52.391697]]]}},{"id":"320822266","type":"Feature","properties":{"levels":1,"type":"garage"},"geometry":{"type":"Polygon","coordinates":[[[13.380561,52.391896],[13.380568,52.391921],[13.380637,52.391915],[13.380631,52.391889],[13.380561,52.391896]]]}},{"id":"320822171","type":"Feature","properties":{"levels":1,"type":"garage"},"geometry":{"type":"Polygon","coordinates":[[[13.381115,52.393896],[13.381126,52.393945],[13.381167,52.393941],[13.381156,52.393893],[13.381115,52.393896]]]}},{"id":"320822141","type":"Feature","properties":{"levels":1,"type":"garage"},"geometry":{"type":"Polygon","coordinates":[[[13.380518,52.391722],[13.380525,52.39175],[13.380594,52.391743],[13.380587,52.391716],[13.380518,52.391722]]]}},{"id":"320822138","type":"Feature","properties":{"levels":2,"type":"terrace"},"geometry":{"type":"Polygon","coordinates":[[[13.380937,52.393634],[13.380949,52.393684],[13.381084,52.393671],[13.381072,52.393621],[13.380937,52.393634]]]}},{"id":"320822109","type":"Feature","properties":{"levels":1,"type":"garage"},"geometry":{"type":"Polygon","coordinates":[[[13.380455,52.39133],[13.380461,52.391356],[13.380542,52.391349],[13.380536,52.391323],[13.380455,52.39133]]]}},{"id":"320822101","type":"Feature","properties":{"levels":1,"type":"garage"},"geometry":{"type":"Polygon","coordinates":[[[13.380951,52.39391],[13.380962,52.39396],[13.381003,52.393956],[13.380992,52.393907],[13.380951,52.39391]]]}},{"id":"320822079","type":"Feature","properties":{"levels":1,"type":"garage"},"geometry":{"type":"Polygon","coordinates":[[[13.380842,52.393798],[13.380854,52.393846],[13.380895,52.393843],[13.380883,52.393794],[13.380842,52.393798]]]}},{"id":"320822064","type":"Feature","properties":{"levels":2,"type":"terrace"},"geometry":{"type":"Polygon","coordinates":[[[13.380632,52.3924],[13.380644,52.39245],[13.38078,52.392438],[13.380768,52.392388],[13.380632,52.3924]]]}},{"id":"320822050","type":"Feature","properties":{"levels":1,"type":"garage"},"geometry":{"type":"Polygon","coordinates":[[[13.381187,52.391516],[13.381195,52.39155],[13.381311,52.391539],[13.381303,52.391505],[13.381187,52.391516]]]}},{"id":"320822044","type":"Feature","properties":{"levels":1,"type":"garage"},"geometry":{"type":"Polygon","coordinates":[[[13.380992,52.393907],[13.381003,52.393956],[13.381044,52.393952],[13.381033,52.393903],[13.380992,52.393907]]]}},{"id":"320822007","type":"Feature","properties":{"levels":2,"type":"terrace"},"geometry":{"type":"Polygon","coordinates":[[[13.380733,52.392828],[13.380746,52.392878],[13.380882,52.392866],[13.380869,52.392816],[13.380733,52.392828]]]}},{"id":"320822006","type":"Feature","properties":{"levels":1,"type":"garage"},"geometry":{"type":"Polygon","coordinates":[[[13.380556,52.391872],[13.380561,52.391896],[13.380631,52.391889],[13.380625,52.391866],[13.380556,52.391872]]]}},{"id":"320821986","type":"Feature","properties":{"levels":1,"type":"garage"},"geometry":{"type":"Polygon","coordinates":[[[13.380962,52.39396],[13.380974,52.394008],[13.381015,52.394005],[13.381003,52.393956],[13.380962,52.39396]]]}},{"id":"320821983","type":"Feature","properties":{"levels":1,"type":"garage"},"geometry":{"type":"Polygon","coordinates":[[[13.381128,52.391322],[13.381139,52.391362],[13.381235,52.391354],[13.381226,52.391313],[13.381128,52.391322]]]}},{"id":"320821980","type":"Feature","properties":{"levels":1,"type":"garage"},"geometry":{"type":"Polygon","coordinates":[[[13.381047,52.393779],[13.381059,52.393828],[13.3811,52.393824],[13.381088,52.393775],[13.381047,52.393779]]]}},{"id":"320821943","type":"Feature","properties":{"levels":2,"type":"terrace"},"geometry":{"type":"Polygon","coordinates":[[[13.380619,52.39235],[13.380632,52.3924],[13.380768,52.392388],[13.380755,52.392338],[13.380619,52.39235]]]}},{"id":"320821902","type":"Feature","properties":{"levels":1,"type":"garage"},"geometry":{"type":"Polygon","coordinates":[[[13.380605,52.39207],[13.380611,52.392094],[13.380682,52.392088],[13.380676,52.392064],[13.380605,52.39207]]]}},{"id":"320823223","type":"Feature","properties":{"levels":2,"type":"terrace"},"geometry":{"type":"Polygon","coordinates":[[[13.381317,52.390924],[13.38134,52.391022],[13.381345,52.391021],[13.381343,52.391015],[13.381377,52.391012],[13.381378,52.391018],[13.381418,52.391015],[13.381395,52.390917],[13.381317,52.390924]]]}},{"id":"320823205","type":"Feature","properties":{"levels":2,"type":"terrace"},"geometry":{"type":"Polygon","coordinates":[[[13.38116,52.390938],[13.381183,52.391036],[13.381186,52.391036],[13.381185,52.39103],[13.381218,52.391027],[13.381219,52.391033],[13.381261,52.391029],[13.381238,52.390931],[13.38116,52.390938]]]}},{"id":"320823186","type":"Feature","properties":{"levels":2,"type":"terrace"},"geometry":{"type":"Polygon","coordinates":[[[13.381238,52.390931],[13.381261,52.391029],[13.381266,52.391028],[13.381264,52.391023],[13.381297,52.39102],[13.381299,52.391025],[13.38134,52.391022],[13.381317,52.390924],[13.381238,52.390931]]]}},{"id":"320823142","type":"Feature","properties":{"levels":1,"type":"garage"},"geometry":{"type":"Polygon","coordinates":[[[13.381326,52.39077],[13.381412,52.39082],[13.381428,52.39081],[13.381428,52.390799],[13.381413,52.39079],[13.381417,52.390787],[13.381356,52.390751],[13.381326,52.39077]]]}},{"id":"320822419","type":"Feature","properties":{"levels":1,"type":"garage"},"geometry":{"type":"Polygon","coordinates":[[[13.380987,52.391014],[13.380994,52.391039],[13.381078,52.391031],[13.381072,52.391006],[13.380987,52.391014]]]}},{"id":"320822001","type":"Feature","properties":{"levels":1,"type":"garage"},"geometry":{"type":"Polygon","coordinates":[[[13.381,52.391064],[13.381006,52.39109],[13.38109,52.391082],[13.381084,52.391057],[13.381,52.391064]]]}},{"id":"320821956","type":"Feature","properties":{"levels":1,"type":"garage"},"geometry":{"type":"Polygon","coordinates":[[[13.380994,52.391039],[13.381,52.391064],[13.381084,52.391057],[13.381078,52.391031],[13.380994,52.391039]]]}},{"id":"320821924","type":"Feature","properties":{"levels":1,"type":"garage"},"geometry":{"type":"Polygon","coordinates":[[[13.380981,52.390989],[13.380987,52.391014],[13.381072,52.391006],[13.381065,52.390981],[13.380981,52.390989]]]}},{"id":"339285330","type":"Feature","properties":{"height":11,"levels":2,"color":"#f2f5f7","roofMaterial":"roof_tiles","roofColor":"#acabaf","roofShape":"skillion","roofLevels":1,"roofDirection":94.60000000000002,"building":"r4807852"},"geometry":{"type":"Polygon","coordinates":[[[13.381066,52.390157],[13.38108,52.390264],[13.381185,52.390259],[13.381172,52.390152],[13.381066,52.390157]]]}},{"id":"339285334","type":"Feature","properties":{"height":11,"levels":2,"color":"#f2f5f7","roofMaterial":"roof_tiles","roofColor":"#acabaf","roofShape":"skillion","roofLevels":1,"roofDirection":94.60000000000002,"building":"r4807845"},"geometry":{"type":"Polygon","coordinates":[[[13.381025,52.389786],[13.381039,52.389893],[13.381144,52.389888],[13.381131,52.389781],[13.381025,52.389786]]]}},{"id":"339285335","type":"Feature","properties":{"height":11,"levels":2,"color":"#f2f5f7","roofMaterial":"roof_tiles","roofColor":"#acabaf","roofShape":"skillion","roofLevels":1,"roofDirection":94.60000000000002,"building":"r4807844"},"geometry":{"type":"Polygon","coordinates":[[[13.381001,52.389599],[13.381015,52.389706],[13.38112,52.389701],[13.381107,52.389594],[13.381001,52.389599]]]}}]}